MANIFEST.in
README.md
setup.py
mercuro/__init__.py
mercuro/mercuro.py
mercuro.egg-info/PKG-INFO
mercuro.egg-info/SOURCES.txt
mercuro.egg-info/dependency_links.txt
mercuro.egg-info/top_level.txt