Metadata-Version: 1.1
Name: mercuro
Version: 0.1.1
Summary: A simple daemon that listens for syslog events and forwards them to a Riemann server.
Home-page: https://github.com/briancline/mercuro
Author: Brian Cline
Author-email: brian.cline@gmail.com
License: Apache
Keywords: syslog rsyslog riemann logging
Platform: UNKNOWN
Classifier: Development Status :: 3 - Alpha
Classifier: License :: OSI Approved :: Apache Software License
Classifier: Intended Audience :: System Administrators
Classifier: Natural Language :: English
Classifier: Operating System :: POSIX :: Linux
Classifier: Programming Language :: Python
Classifier: Programming Language :: Python :: 2.7
